README.rst
setup.py
pyfiltration/__init__.py
pyfiltration.egg-info/PKG-INFO
pyfiltration.egg-info/SOURCES.txt
pyfiltration.egg-info/dependency_links.txt
pyfiltration.egg-info/not-zip-safe
pyfiltration.egg-info/top_level.txt