Metadata-Version: 1.0
Name: pyfiltration
Version: 1.0.9
Summary: tornado filtration
Home-page: https://github.com/nashuiliang/pyfiltration
Author: chuangwang
Author-email: nashuiliang@gmail.com
License: Apache License 2.0
Keywords: tornado argument get_argument filter filtration
Platform: UNKNOWN
